{
  "data": [
      {
        "first_name": "Aaron",
        "last_name": "Swartz"
      },
      {
        "first_name": "Ada",
        "last_name": "Lovelace"
      },
      {
        "first_name": "Adrian",
        "last_name": "Holovaty"
      },
      {
        "first_name": "Alan",
        "last_name": "Turing"
      },
      {
        "first_name": "Audrey",
        "last_name": "Roy Greenfeld"
      },
      {
        "first_name": "Chelsea",
        "last_name": "Manning"
      },
      {
        "first_name": "Daniel",
        "last_name": "Roy Greenfeld"
      },
      {
        "first_name": "Donald",
        "last_name": "Knuth"
      },
      {
        "first_name": "Edward",
        "last_name": "Snowden"
      },
      {
        "first_name": "Grace",
        "last_name": "Hopper"
      },
      {
        "first_name": "Guido",
        "last_name": "Van Rossum"
      },
      {
        "first_name": "Ian",
        "last_name": "Murdock"
      },
      {
        "first_name": "Jacob",
        "last_name": "Kaplan Moss"
      },
      {
        "first_name": "Linus",
        "last_name": "Torvalds"
      },
      {
        "first_name": "Peter",
        "last_name": "Baumgartner"
      },
      {
        "first_name": "Simon",
        "last_name": "Willison"
      }
    ]
}